Metadata-Version: 2.1
Name: pytest-status
Version: 0.1.1
Summary: Add status mark for tests
Home-page: https://github.com/hanzhichao/pytest-status
Author: Han Zhichao
Author-email: superhin@126.com
License: MIT license
Keywords: pytest,py.test,pytest-status,test status,pytest tester
Classifier: Framework :: Pytest
Classifier: Programming Language :: Python
Classifier: Topic :: Software Development :: Testing
Classifier: Programming Language :: Python :: 3.6
License-File: LICENSE
Requires-Dist: pytest
Requires-Dist: pytest-runner
